pysupuesto/__init__.py
pysupuesto-0.2.3.dist-info/METADATA
pysupuesto-0.2.3.dist-info/WHEEL
pysupuesto-0.2.3.dist-info/top_level.txt
pysupuesto-0.2.3.dist-info/RECORD
