Metadata-Version: 2.1
Name: pysupuesto
Version: 0.2.3
Summary: Módulo para descargar bases de diferentes ejercicios (o series temporales) del presupuesto público nacional argentino desde el Ministerio de Economía
Home-page: 
Author: @Mato
Author-email: no@email.org
License: MIT
Keywords: presupuesto,budget
Classifier: Development Status :: 1 - Planning
Classifier: Intended Audience :: Other Audience
Classifier: Operating System :: POSIX :: Linux
Classifier: License :: OSI Approved :: MIT License
Classifier: Programming Language :: Python :: 3
